djangojr/__init__.py
djangojr/authentication.py
djangojr/pagenation.py
djangojr/permissions.py
djangojr/rate_limit.py
djangojr/serializer.py
djangojr/utils.py
djangojr/ratelimit/__init__.py
djangojr/ratelimit/admin.py
djangojr/ratelimit/apps.py
djangojr/ratelimit/models.py
djangojr/ratelimit/utils.py
djangojr/ratelimit/migrations/__init__.py
djangojr/token/__init__.py
djangojr/token/admin.py
djangojr/token/apps.py
djangojr/token/models.py
djangojr/token/migrations/__init__.py
djangojr-1.0.5.dist-info/LICENSE
djangojr-1.0.5.dist-info/METADATA
djangojr-1.0.5.dist-info/WHEEL
djangojr-1.0.5.dist-info/top_level.txt
djangojr-1.0.5.dist-info/RECORD
