Metadata-Version: 2.1
Name: djangojr
Version: 1.0.5
Summary: Django app to json rest api provide api views, serializer, rate limit, pagination, authentication, permission,lazy response,blacklist etc.
Home-page: https://github.com/esrefyigitbasi-dev/django_json_rest
Author: Esref Yigitbasi
Author-email: esrefyigitbasi.dev@gmail.com
License: MIT
Keywords: django restframework djangojr json parse response request api wrapper lazyresponse ratelimit pagination permissions token authentication
Classifier: Intended Audience :: Developers
Classifier: License :: OSI Approved :: MIT License
Classifier: Programming Language :: Python :: 3
Classifier: Programming Language :: Python :: 3.3
Classifier: Programming Language :: Python :: 3.4
Classifier: Programming Language :: Python :: 3.5
Classifier: Programming Language :: Python :: 3.6
Classifier: Programming Language :: Python :: 3.7
Classifier: Programming Language :: Python :: 3.8
Classifier: Programming Language :: Python :: 3.9
License-File: LICENSE
Requires-Dist: djangorestframework
